SuperSimpleGameHacker/English.py
SuperSimpleGameHacker/Portugues.py
SuperSimpleGameHacker/__init__.py
SuperSimpleGameHacker-2025.dist-info/METADATA
SuperSimpleGameHacker-2025.dist-info/WHEEL
SuperSimpleGameHacker-2025.dist-info/top_level.txt
SuperSimpleGameHacker-2025.dist-info/RECORD
