Metadata-Version: 2.1
Name: SuperSimpleGameHacker
Version: 2025
Summary: Super Simple Game Hacker criando por GabrielLLPontes
Author: GabrielLLPontesOficial
Author-email: gabrielpontesoficial93@gmail.com
Classifier: Programming Language :: Python :: 3
Classifier: License :: OSI Approved :: MIT License
Classifier: Operating System :: OS Independent
Requires-Python: >=3.6
Requires-Dist: pymem
